langchain_taiga/__init__.py
langchain_taiga/py.typed
langchain_taiga/toolkits.py
langchain_taiga/tools/__init__.py
langchain_taiga/tools/taiga_tools.py
langchain_taiga-1.1.1.dist-info/LICENSE
langchain_taiga-1.1.1.dist-info/METADATA
langchain_taiga-1.1.1.dist-info/WHEEL
langchain_taiga-1.1.1.dist-info/RECORD
