Metadata-Version: 2.3
Name: langchain-taiga
Version: 1.1.1
Summary: Python toolkit that lets your LangChain agents automate Taiga: create, search, edit & comment on user stories, tasks and issues via the official REST API.
License: MIT
Requires-Python: >=3.9,<4.0
Classifier: License :: OSI Approved :: MIT License
Classifier: Programming Language :: Python :: 3
Classifier: Programming Language :: Python :: 3.9
Classifier: Programming Language :: Python :: 3.10
Classifier: Programming Language :: Python :: 3.11
Classifier: Programming Language :: Python :: 3.12
Classifier: Programming Language :: Python :: 3.13
Requires-Dist: cachetools (>=5.5.2,<6.0.0)
Requires-Dist: langchain-core (>=0.3.15,<0.4.0)
Requires-Dist: langchain-ollama (>=0.3.2,<0.4.0)
Requires-Dist: langchain-openai (>=0.3.14,<0.4.0)
Requires-Dist: python-dotenv (>=1.1.0,<2.0.0)
Requires-Dist: python-taiga (>=1.3.2,<2.0.0)
Project-URL: Repository, https://github.com/Shikenso-Analytics/langchain-taiga
Project-URL: Release Notes, https://github.com/Shikenso-Analytics/langchain-taiga/releases
Project-URL: Source Code, https://github.com/Shikenso-Analytics/langchain-taiga
